{"mc":{
	"210_tianbing":{
		"frameRate":12,
		"labels":[
			{"name":"idle","frame":1,"end":12}
			,{"name":"attack","frame":13,"end":24}
			,{"name":"attacked","frame":25,"end":32}
			
			],
		"events":[
			
			],
		"frames":[
			
			{
			"res":"6686ECD2",
			"x":-53,
			"y":-75
			},
			{
			"res":"5A5D7701",
			"x":-53,
			"y":-75
			},
			{
			"res":"2DDBAFF9",
			"x":-53,
			"y":-74
			},
			{
			"res":"82AE0712",
			"x":-54,
			"y":-74
			},
			{
			"res":"E99D8B4F",
			"x":-53,
			"y":-74
			},
			{
			"res":"412A445F",
			"x":-53,
			"y":-74
			},
			{
			"res":"D074BD10",
			"x":-53,
			"y":-74
			},
			{
			"res":"491719BF",
			"x":-54,
			"y":-74
			},
			{
			"res":"4520ABB",
			"x":-54,
			"y":-74
			},
			{
			"res":"640C839E",
			"x":-53,
			"y":-75
			},
			{
			"res":"EAAE0878",
			"x":-53,
			"y":-75
			},
			{
			"res":"6686ECD2",
			"x":-53,
			"y":-75,
			"duration":2
			},
			{
			"res":"E1A0F8FD",
			"x":-53,
			"y":-74
			},
			{
			"res":"49CFAD5E",
			"x":-49,
			"y":-74
			},
			{
			"res":"7D39588A",
			"x":-42,
			"y":-74
			},
			{
			"res":"C3B9B48B",
			"x":-89,
			"y":-72
			},
			{
			"res":"B5BD5111",
			"x":-87,
			"y":-72
			},
			{
			"res":"9FEDCFFA",
			"x":-85,
			"y":-72
			},
			{
			"res":"1817DA5A",
			"x":-79,
			"y":-73
			},
			{
			"res":"59F016C8",
			"x":-73,
			"y":-73
			},
			{
			"res":"DBD2AEF9",
			"x":-67,
			"y":-74
			},
			{
			"res":"278C4AD7",
			"x":-60,
			"y":-75
			},
			{
			"res":"6686ECD2",
			"x":-53,
			"y":-75
			},
			{
			"res":"1E4FCFD6",
			"x":-53,
			"y":-67
			},
			{
			"res":"14259C46",
			"x":-43,
			"y":-74
			},
			{
			"res":"C8428D86",
			"x":-39,
			"y":-68
			},
			{
			"res":"4635867E",
			"x":-33,
			"y":-70
			},
			{
			"res":"4A91C51A",
			"x":-22,
			"y":-77
			},
			{
			"res":"4E760165",
			"x":-55,
			"y":-75
			},
			{
			"res":"D54415A9",
			"x":-54,
			"y":-74
			},
			{
			"res":"6686ECD2",
			"x":-53,
			"y":-75
			}
			]
}},
	"res":{
		"412A445F":{"x":85,"y":319,"w":81,"h":75},
		"E99D8B4F":{"x":251,"y":320,"w":81,"h":75},
		"D54415A9":{"x":88,"y":164,"w":84,"h":75},
		"DBD2AEF9":{"x":182,"y":84,"w":88,"h":75},
		"C3B9B48B":{"x":1,"y":1,"w":103,"h":81},
		"9FEDCFFA":{"x":209,"y":1,"w":99,"h":81},
		"1E4FCFD6":{"x":310,"y":81,"w":84,"h":82},
		"491719BF":{"x":174,"y":239,"w":83,"h":75},
		"640C839E":{"x":343,"y":315,"w":82,"h":75},
		"4E760165":{"x":94,"y":84,"w":86,"h":78},
		"49CFAD5E":{"x":1,"y":161,"w":85,"h":75},
		"82AE0712":{"x":259,"y":243,"w":82,"h":75},
		"2DDBAFF9":{"x":168,"y":316,"w":81,"h":75},
		"59F016C8":{"x":1,"y":84,"w":91,"h":75},
		"EAAE0878":{"x":1,"y":238,"w":82,"h":76},
		"5A5D7701":{"x":85,"y":241,"w":81,"h":76},
		"B5BD5111":{"x":106,"y":1,"w":101,"h":81},
		"4A91C51A":{"x":406,"y":1,"w":83,"h":83},
		"E1A0F8FD":{"x":334,"y":392,"w":81,"h":75},
		"D074BD10":{"x":427,"y":315,"w":82,"h":75},
		"4520ABB":{"x":396,"y":163,"w":84,"h":75},
		"6686ECD2":{"x":267,"y":165,"w":82,"h":76},
		"278C4AD7":{"x":182,"y":161,"w":83,"h":76},
		"4635867E":{"x":351,"y":240,"w":85,"h":73},
		"1817DA5A":{"x":310,"y":1,"w":94,"h":78},
		"C8428D86":{"x":417,"y":392,"w":87,"h":69},
		"7D39588A":{"x":396,"y":86,"w":86,"h":75},
		"14259C46":{"x":1,"y":316,"w":82,"h":75}
	}}