{
	"1": {
		"type_child": 1,
		"achv_parm": 10,
		"name": "漫漫取经路",
		"disc": "闯过第 10 关",
		"reward_1": [
			"3",
			"0",
			"50"
		],
		"next_id": 2,
		"achv_type": 1,
		"id": 1
	},
	"2": {
		"type_child": 2,
		"achv_parm": 50,
		"name": "漫漫取经路",
		"disc": "闯过第 50 关",
		"reward_1": [
			"3",
			"0",
			"50"
		],
		"next_id": 3,
		"achv_type": 1,
		"id": 2
	},
	"3": {
		"type_child": 3,
		"achv_parm": 100,
		"name": "漫漫取经路",
		"disc": "闯过第 100 关",
		"reward_1": [
			"3",
			"0",
			"50"
		],
		"next_id": 4,
		"achv_type": 1,
		"id": 3
	},
	"4": {
		"type_child": 4,
		"achv_parm": 200,
		"name": "漫漫取经路",
		"disc": "闯过第 200 关",
		"reward_1": [
			"3",
			"0",
			"50"
		],
		"next_id": 5,
		"achv_type": 1,
		"id": 4
	},
	"5": {
		"type_child": 5,
		"achv_parm": 300,
		"name": "漫漫取经路",
		"disc": "闯过第 300 关",
		"reward_1": [
			"3",
			"0",
			"50"
		],
		"next_id": 6,
		"achv_type": 1,
		"id": 5
	},
	"6": {
		"type_child": 6,
		"achv_parm": 500,
		"name": "漫漫取经路",
		"disc": "闯过第 500 关",
		"reward_1": [
			"3",
			"0",
			"50"
		],
		"next_id": 7,
		"achv_type": 1,
		"id": 6
	},
	"7": {
		"type_child": 7,
		"achv_parm": 700,
		"name": "漫漫取经路",
		"disc": "闯过第 700 关",
		"reward_1": [
			"3",
			"0",
			"50"
		],
		"next_id": 8,
		"achv_type": 1,
		"id": 7
	},
	"8": {
		"type_child": 8,
		"achv_parm": 1000,
		"name": "漫漫取经路",
		"disc": "闯过第 1000 关",
		"reward_1": [
			"3",
			"0",
			"50"
		],
		"next_id": 9,
		"achv_type": 1,
		"id": 8
	},
	"9": {
		"type_child": 9,
		"achv_parm": 1300,
		"name": "漫漫取经路",
		"disc": "闯过第 1300 关",
		"reward_1": [
			"3",
			"0",
			"50"
		],
		"next_id": 10,
		"achv_type": 1,
		"id": 9
	},
	"10": {
		"type_child": 10,
		"achv_parm": 1600,
		"name": "漫漫取经路",
		"disc": "闯过第 1600 关",
		"reward_1": [
			"3",
			"0",
			"50"
		],
		"next_id": 11,
		"achv_type": 1,
		"id": 10
	},
	"11": {
		"type_child": 11,
		"achv_parm": 2000,
		"name": "漫漫取经路",
		"disc": "闯过第 2000 关",
		"reward_1": [
			"3",
			"0",
			"50"
		],
		"next_id": 12,
		"achv_type": 1,
		"id": 11
	},
	"12": {
		"type_child": 12,
		"achv_parm": 2500,
		"name": "漫漫取经路",
		"disc": "闯过第 2500 关",
		"reward_1": [
			"3",
			"0",
			"50"
		],
		"next_id": 13,
		"achv_type": 1,
		"id": 12
	},
	"13": {
		"type_child": 13,
		"achv_parm": 3000,
		"name": "漫漫取经路",
		"disc": "闯过第 3000 关",
		"reward_1": [
			"3",
			"0",
			"50"
		],
		"next_id": 14,
		"achv_type": 1,
		"id": 13
	},
	"14": {
		"type_child": 14,
		"achv_parm": 4000,
		"name": "漫漫取经路",
		"disc": "闯过第 4000 关",
		"reward_1": [
			"3",
			"0",
			"50"
		],
		"next_id": 15,
		"achv_type": 1,
		"id": 14
	},
	"15": {
		"type_child": 15,
		"achv_parm": 5000,
		"name": "漫漫取经路",
		"disc": "闯过第 5000 关",
		"reward_1": [
			"3",
			"0",
			"50"
		],
		"next_id": 16,
		"achv_type": 1,
		"id": 15
	},
	"16": {
		"type_child": 16,
		"achv_parm": 6000,
		"name": "漫漫取经路",
		"disc": "闯过第 6000 关",
		"reward_1": [
			"3",
			"0",
			"50"
		],
		"next_id": 0,
		"achv_type": 1,
		"id": 16
	},
	"17": {
		"type_child": 1,
		"achv_parm": 5,
		"name": "战场宝箱开启数量",
		"disc": "点击 5 次小事件",
		"reward_1": [
			"3",
			"0",
			"50"
		],
		"next_id": 18,
		"achv_type": 2,
		"id": 17
	},
	"18": {
		"type_child": 2,
		"achv_parm": 50,
		"name": "战场宝箱开启数量",
		"disc": "点击 50 次小事件",
		"reward_1": [
			"3",
			"0",
			"50"
		],
		"next_id": 19,
		"achv_type": 2,
		"id": 18
	},
	"19": {
		"type_child": 3,
		"achv_parm": 500,
		"name": "战场宝箱开启数量",
		"disc": "点击 500 次小事件",
		"reward_1": [
			"3",
			"0",
			"50"
		],
		"next_id": 20,
		"achv_type": 2,
		"id": 19
	},
	"20": {
		"type_child": 4,
		"achv_parm": 5000,
		"name": "战场宝箱开启数量",
		"disc": "点击 5000 次小事件",
		"reward_1": [
			"3",
			"0",
			"50"
		],
		"next_id": 21,
		"achv_type": 2,
		"id": 20
	},
	"21": {
		"type_child": 5,
		"achv_parm": 50000,
		"name": "战场宝箱开启数量",
		"disc": "点击 50000 次小事件",
		"reward_1": [
			"3",
			"0",
			"50"
		],
		"next_id": 22,
		"achv_type": 2,
		"id": 21
	},
	"22": {
		"type_child": 6,
		"achv_parm": 500000,
		"name": "战场宝箱开启数量",
		"disc": "点击 500000 次小事件",
		"reward_1": [
			"3",
			"0",
			"50"
		],
		"next_id": 0,
		"achv_type": 2,
		"id": 22
	},
	"23": {
		"type_child": 1,
		"achv_parm": 1,
		"name": "轮回次数",
		"disc": "进行 1 次轮回",
		"reward_1": [
			"3",
			"0",
			"50"
		],
		"next_id": 24,
		"achv_type": 3,
		"id": 23
	},
	"24": {
		"type_child": 2,
		"achv_parm": 3,
		"name": "轮回次数",
		"disc": "进行 3 次轮回",
		"reward_1": [
			"3",
			"0",
			"50"
		],
		"next_id": 25,
		"achv_type": 3,
		"id": 24
	},
	"25": {
		"type_child": 3,
		"achv_parm": 8,
		"name": "轮回次数",
		"disc": "进行 8 次轮回",
		"reward_1": [
			"3",
			"0",
			"50"
		],
		"next_id": 26,
		"achv_type": 3,
		"id": 25
	},
	"26": {
		"type_child": 4,
		"achv_parm": 15,
		"name": "轮回次数",
		"disc": "进行 15 次轮回",
		"reward_1": [
			"3",
			"0",
			"50"
		],
		"next_id": 27,
		"achv_type": 3,
		"id": 26
	},
	"27": {
		"type_child": 5,
		"achv_parm": 30,
		"name": "轮回次数",
		"disc": "进行 30 次轮回",
		"reward_1": [
			"3",
			"0",
			"50"
		],
		"next_id": 28,
		"achv_type": 3,
		"id": 27
	},
	"28": {
		"type_child": 6,
		"achv_parm": 50,
		"name": "轮回次数",
		"disc": "进行 50 次轮回",
		"reward_1": [
			"3",
			"0",
			"50"
		],
		"next_id": 29,
		"achv_type": 3,
		"id": 28
	},
	"29": {
		"type_child": 7,
		"achv_parm": 100,
		"name": "轮回次数",
		"disc": "进行 100 次轮回",
		"reward_1": [
			"3",
			"0",
			"50"
		],
		"next_id": 30,
		"achv_type": 3,
		"id": 29
	},
	"30": {
		"type_child": 8,
		"achv_parm": 200,
		"name": "轮回次数",
		"disc": "进行 200 次轮回",
		"reward_1": [
			"3",
			"0",
			"50"
		],
		"next_id": 31,
		"achv_type": 3,
		"id": 30
	},
	"31": {
		"type_child": 9,
		"achv_parm": 500,
		"name": "轮回次数",
		"disc": "进行 500 次轮回",
		"reward_1": [
			"3",
			"0",
			"50"
		],
		"next_id": 32,
		"achv_type": 3,
		"id": 31
	},
	"32": {
		"type_child": 10,
		"achv_parm": 1000,
		"name": "轮回次数",
		"disc": "进行 1000 次轮回",
		"reward_1": [
			"3",
			"0",
			"50"
		],
		"next_id": 0,
		"achv_type": 3,
		"id": 32
	},
	"33": {
		"type_child": 1,
		"achv_parm": 20,
		"name": "累计请仙次数",
		"disc": "进行 20 次请仙",
		"reward_1": [
			"3",
			"0",
			"50"
		],
		"next_id": 34,
		"achv_type": 4,
		"id": 33
	},
	"34": {
		"type_child": 2,
		"achv_parm": 200,
		"name": "累计请仙次数",
		"disc": "进行 200 次请仙",
		"reward_1": [
			"3",
			"0",
			"50"
		],
		"next_id": 35,
		"achv_type": 4,
		"id": 34
	},
	"35": {
		"type_child": 3,
		"achv_parm": 2000,
		"name": "累计请仙次数",
		"disc": "进行 2000 次请仙",
		"reward_1": [
			"3",
			"0",
			"50"
		],
		"next_id": 36,
		"achv_type": 4,
		"id": 35
	},
	"36": {
		"type_child": 4,
		"achv_parm": 20000,
		"name": "累计请仙次数",
		"disc": "进行 20000 次请仙",
		"reward_1": [
			"3",
			"0",
			"50"
		],
		"next_id": 0,
		"achv_type": 4,
		"id": 36
	},
	"37": {
		"type_child": 1,
		"achv_parm": 3,
		"name": "拥有伙伴数量",
		"disc": "获得 3 位西游伙伴",
		"reward_1": [
			"3",
			"0",
			"50"
		],
		"next_id": 38,
		"achv_type": 5,
		"id": 37
	},
	"38": {
		"type_child": 2,
		"achv_parm": 6,
		"name": "拥有伙伴数量",
		"disc": "获得 6 位西游伙伴",
		"reward_1": [
			"3",
			"0",
			"50"
		],
		"next_id": 39,
		"achv_type": 5,
		"id": 38
	},
	"39": {
		"type_child": 3,
		"achv_parm": 10,
		"name": "拥有伙伴数量",
		"disc": "获得 10 位西游伙伴",
		"reward_1": [
			"3",
			"0",
			"50"
		],
		"next_id": 40,
		"achv_type": 5,
		"id": 39
	},
	"40": {
		"type_child": 4,
		"achv_parm": 15,
		"name": "拥有伙伴数量",
		"disc": "获得 15 位西游伙伴",
		"reward_1": [
			"3",
			"0",
			"50"
		],
		"next_id": 41,
		"achv_type": 5,
		"id": 40
	},
	"41": {
		"type_child": 5,
		"achv_parm": 20,
		"name": "拥有伙伴数量",
		"disc": "获得 20 位西游伙伴",
		"reward_1": [
			"3",
			"0",
			"50"
		],
		"next_id": 42,
		"achv_type": 5,
		"id": 41
	},
	"42": {
		"type_child": 6,
		"achv_parm": 25,
		"name": "拥有伙伴数量",
		"disc": "获得 25 位西游伙伴",
		"reward_1": [
			"3",
			"0",
			"50"
		],
		"next_id": 43,
		"achv_type": 5,
		"id": 42
	},
	"43": {
		"type_child": 7,
		"achv_parm": 30,
		"name": "拥有伙伴数量",
		"disc": "获得 30 位西游伙伴",
		"reward_1": [
			"3",
			"0",
			"50"
		],
		"next_id": 0,
		"achv_type": 5,
		"id": 43
	},
	"44": {
		"type_child": 1,
		"achv_parm": 10,
		"name": "伙伴强化最高等级",
		"disc": "最高强化等级达到 +10",
		"reward_1": [
			"3",
			"0",
			"50"
		],
		"next_id": 45,
		"achv_type": 6,
		"id": 44
	},
	"45": {
		"type_child": 2,
		"achv_parm": 25,
		"name": "伙伴强化最高等级",
		"disc": "最高强化等级达到 +25",
		"reward_1": [
			"3",
			"0",
			"50"
		],
		"next_id": 46,
		"achv_type": 6,
		"id": 45
	},
	"46": {
		"type_child": 3,
		"achv_parm": 50,
		"name": "伙伴强化最高等级",
		"disc": "最高强化等级达到 +50",
		"reward_1": [
			"3",
			"0",
			"50"
		],
		"next_id": 47,
		"achv_type": 6,
		"id": 46
	},
	"47": {
		"type_child": 4,
		"achv_parm": 100,
		"name": "伙伴强化最高等级",
		"disc": "最高强化等级达到 +100",
		"reward_1": [
			"3",
			"0",
			"50"
		],
		"next_id": 48,
		"achv_type": 6,
		"id": 47
	},
	"48": {
		"type_child": 5,
		"achv_parm": 200,
		"name": "伙伴强化最高等级",
		"disc": "最高强化等级达到 +200",
		"reward_1": [
			"3",
			"0",
			"50"
		],
		"next_id": 49,
		"achv_type": 6,
		"id": 48
	},
	"49": {
		"type_child": 6,
		"achv_parm": 300,
		"name": "伙伴强化最高等级",
		"disc": "最高强化等级达到 +300",
		"reward_1": [
			"3",
			"0",
			"50"
		],
		"next_id": 50,
		"achv_type": 6,
		"id": 49
	},
	"50": {
		"type_child": 7,
		"achv_parm": 400,
		"name": "伙伴强化最高等级",
		"disc": "最高强化等级达到 +400",
		"reward_1": [
			"3",
			"0",
			"50"
		],
		"next_id": 51,
		"achv_type": 6,
		"id": 50
	},
	"51": {
		"type_child": 8,
		"achv_parm": 500,
		"name": "伙伴强化最高等级",
		"disc": "最高强化等级达到 +500",
		"reward_1": [
			"3",
			"0",
			"50"
		],
		"next_id": 52,
		"achv_type": 6,
		"id": 51
	},
	"52": {
		"type_child": 9,
		"achv_parm": 600,
		"name": "伙伴强化最高等级",
		"disc": "最高强化等级达到 +600",
		"reward_1": [
			"3",
			"0",
			"50"
		],
		"next_id": 53,
		"achv_type": 6,
		"id": 52
	},
	"53": {
		"type_child": 10,
		"achv_parm": 700,
		"name": "伙伴强化最高等级",
		"disc": "最高强化等级达到 +700",
		"reward_1": [
			"3",
			"0",
			"50"
		],
		"next_id": 54,
		"achv_type": 6,
		"id": 53
	},
	"54": {
		"type_child": 11,
		"achv_parm": 800,
		"name": "伙伴强化最高等级",
		"disc": "最高强化等级达到 +800",
		"reward_1": [
			"3",
			"0",
			"50"
		],
		"next_id": 55,
		"achv_type": 6,
		"id": 54
	},
	"55": {
		"type_child": 12,
		"achv_parm": 900,
		"name": "伙伴强化最高等级",
		"disc": "最高强化等级达到 +900",
		"reward_1": [
			"3",
			"0",
			"50"
		],
		"next_id": 56,
		"achv_type": 6,
		"id": 55
	},
	"56": {
		"type_child": 13,
		"achv_parm": 1000,
		"name": "伙伴强化最高等级",
		"disc": "最高强化等级达到 +1000",
		"reward_1": [
			"3",
			"0",
			"50"
		],
		"next_id": 57,
		"achv_type": 6,
		"id": 56
	},
	"57": {
		"type_child": 14,
		"achv_parm": 1100,
		"name": "伙伴强化最高等级",
		"disc": "最高强化等级达到 +1100",
		"reward_1": [
			"3",
			"0",
			"50"
		],
		"next_id": 58,
		"achv_type": 6,
		"id": 57
	},
	"58": {
		"type_child": 15,
		"achv_parm": 1200,
		"name": "伙伴强化最高等级",
		"disc": "最高强化等级达到 +1200",
		"reward_1": [
			"3",
			"0",
			"50"
		],
		"next_id": 59,
		"achv_type": 6,
		"id": 58
	},
	"59": {
		"type_child": 16,
		"achv_parm": 1300,
		"name": "伙伴强化最高等级",
		"disc": "最高强化等级达到 +1300",
		"reward_1": [
			"3",
			"0",
			"50"
		],
		"next_id": 60,
		"achv_type": 6,
		"id": 59
	},
	"60": {
		"type_child": 17,
		"achv_parm": 1400,
		"name": "伙伴强化最高等级",
		"disc": "最高强化等级达到 +1400",
		"reward_1": [
			"3",
			"0",
			"50"
		],
		"next_id": 61,
		"achv_type": 6,
		"id": 60
	},
	"61": {
		"type_child": 18,
		"achv_parm": 1500,
		"name": "伙伴强化最高等级",
		"disc": "最高强化等级达到 +1500",
		"reward_1": [
			"3",
			"0",
			"50"
		],
		"next_id": 62,
		"achv_type": 6,
		"id": 61
	},
	"62": {
		"type_child": 19,
		"achv_parm": 1600,
		"name": "伙伴强化最高等级",
		"disc": "最高强化等级达到 +1600",
		"reward_1": [
			"3",
			"0",
			"50"
		],
		"next_id": 63,
		"achv_type": 6,
		"id": 62
	},
	"63": {
		"type_child": 20,
		"achv_parm": 1700,
		"name": "伙伴强化最高等级",
		"disc": "最高强化等级达到 +1700",
		"reward_1": [
			"3",
			"0",
			"50"
		],
		"next_id": 64,
		"achv_type": 6,
		"id": 63
	},
	"64": {
		"type_child": 21,
		"achv_parm": 1800,
		"name": "伙伴强化最高等级",
		"disc": "最高强化等级达到 +1800",
		"reward_1": [
			"3",
			"0",
			"50"
		],
		"next_id": 65,
		"achv_type": 6,
		"id": 64
	},
	"65": {
		"type_child": 22,
		"achv_parm": 1900,
		"name": "伙伴强化最高等级",
		"disc": "最高强化等级达到 +1900",
		"reward_1": [
			"3",
			"0",
			"50"
		],
		"next_id": 66,
		"achv_type": 6,
		"id": 65
	},
	"66": {
		"type_child": 23,
		"achv_parm": 2000,
		"name": "伙伴强化最高等级",
		"disc": "最高强化等级达到 +2000",
		"reward_1": [
			"3",
			"0",
			"50"
		],
		"next_id": 0,
		"achv_type": 6,
		"id": 66
	},
	"67": {
		"type_child": 1,
		"achv_parm": 5,
		"name": "累计伙伴升星次数",
		"disc": "进行 5 次伙伴升星",
		"reward_1": [
			"3",
			"0",
			"50"
		],
		"next_id": 68,
		"achv_type": 7,
		"id": 67
	},
	"68": {
		"type_child": 2,
		"achv_parm": 10,
		"name": "累计伙伴升星次数",
		"disc": "进行 10 次伙伴升星",
		"reward_1": [
			"3",
			"0",
			"50"
		],
		"next_id": 69,
		"achv_type": 7,
		"id": 68
	},
	"69": {
		"type_child": 3,
		"achv_parm": 20,
		"name": "累计伙伴升星次数",
		"disc": "进行 20 次伙伴升星",
		"reward_1": [
			"3",
			"0",
			"50"
		],
		"next_id": 70,
		"achv_type": 7,
		"id": 69
	},
	"70": {
		"type_child": 4,
		"achv_parm": 50,
		"name": "累计伙伴升星次数",
		"disc": "进行 50 次伙伴升星",
		"reward_1": [
			"3",
			"0",
			"50"
		],
		"next_id": 71,
		"achv_type": 7,
		"id": 70
	},
	"71": {
		"type_child": 5,
		"achv_parm": 100,
		"name": "累计伙伴升星次数",
		"disc": "进行 100 次伙伴升星",
		"reward_1": [
			"3",
			"0",
			"50"
		],
		"next_id": 0,
		"achv_type": 7,
		"id": 71
	},
	"72": {
		"type_child": 1,
		"achv_parm": 1,
		"name": "解锁情缘",
		"disc": "解锁 1 组伙伴情缘",
		"reward_1": [
			"3",
			"0",
			"50"
		],
		"next_id": 73,
		"achv_type": 8,
		"id": 72
	},
	"73": {
		"type_child": 2,
		"achv_parm": 5,
		"name": "解锁情缘",
		"disc": "解锁 5 组伙伴情缘",
		"reward_1": [
			"3",
			"0",
			"50"
		],
		"next_id": 74,
		"achv_type": 8,
		"id": 73
	},
	"74": {
		"type_child": 3,
		"achv_parm": 10,
		"name": "解锁情缘",
		"disc": "解锁 10 组伙伴情缘",
		"reward_1": [
			"3",
			"0",
			"50"
		],
		"next_id": 75,
		"achv_type": 8,
		"id": 74
	},
	"75": {
		"type_child": 4,
		"achv_parm": 20,
		"name": "解锁情缘",
		"disc": "解锁 20 组伙伴情缘",
		"reward_1": [
			"3",
			"0",
			"50"
		],
		"next_id": 76,
		"achv_type": 8,
		"id": 75
	},
	"76": {
		"type_child": 5,
		"achv_parm": 30,
		"name": "解锁情缘",
		"disc": "解锁 30 组伙伴情缘",
		"reward_1": [
			"3",
			"0",
			"50"
		],
		"next_id": 0,
		"achv_type": 8,
		"id": 76
	},
	"77": {
		"type_child": 1,
		"achv_parm": 3,
		"name": "收服的小妖数量",
		"disc": "收服 3 只小妖",
		"reward_1": [
			"3",
			"0",
			"50"
		],
		"next_id": 78,
		"achv_type": 9,
		"id": 77
	},
	"78": {
		"type_child": 2,
		"achv_parm": 6,
		"name": "收服的小妖数量",
		"disc": "收服 6 只小妖",
		"reward_1": [
			"3",
			"0",
			"50"
		],
		"next_id": 79,
		"achv_type": 9,
		"id": 78
	},
	"79": {
		"type_child": 3,
		"achv_parm": 10,
		"name": "收服的小妖数量",
		"disc": "收服 10 只小妖",
		"reward_1": [
			"3",
			"0",
			"50"
		],
		"next_id": 80,
		"achv_type": 9,
		"id": 79
	},
	"80": {
		"type_child": 4,
		"achv_parm": 15,
		"name": "收服的小妖数量",
		"disc": "收服 15 只小妖",
		"reward_1": [
			"3",
			"0",
			"50"
		],
		"next_id": 81,
		"achv_type": 9,
		"id": 80
	},
	"81": {
		"type_child": 5,
		"achv_parm": 20,
		"name": "收服的小妖数量",
		"disc": "收服 20 只小妖",
		"reward_1": [
			"3",
			"0",
			"50"
		],
		"next_id": 82,
		"achv_type": 9,
		"id": 81
	},
	"82": {
		"type_child": 6,
		"achv_parm": 25,
		"name": "收服的小妖数量",
		"disc": "收服 25 只小妖",
		"reward_1": [
			"3",
			"0",
			"50"
		],
		"next_id": 83,
		"achv_type": 9,
		"id": 82
	},
	"83": {
		"type_child": 7,
		"achv_parm": 30,
		"name": "收服的小妖数量",
		"disc": "收服 30 只小妖",
		"reward_1": [
			"3",
			"0",
			"50"
		],
		"next_id": 0,
		"achv_type": 9,
		"id": 83
	},
	"84": {
		"type_child": 1,
		"achv_parm": 1,
		"name": "小妖总等级",
		"disc": "小妖总等级达到 1级",
		"reward_1": [
			"3",
			"0",
			"50"
		],
		"next_id": 85,
		"achv_type": 10,
		"id": 84
	},
	"85": {
		"type_child": 2,
		"achv_parm": 3,
		"name": "小妖总等级",
		"disc": "小妖总等级达到 3级",
		"reward_1": [
			"3",
			"0",
			"50"
		],
		"next_id": 86,
		"achv_type": 10,
		"id": 85
	},
	"86": {
		"type_child": 3,
		"achv_parm": 8,
		"name": "小妖总等级",
		"disc": "小妖总等级达到 8级",
		"reward_1": [
			"3",
			"0",
			"50"
		],
		"next_id": 87,
		"achv_type": 10,
		"id": 86
	},
	"87": {
		"type_child": 4,
		"achv_parm": 15,
		"name": "小妖总等级",
		"disc": "小妖总等级达到 15级",
		"reward_1": [
			"3",
			"0",
			"50"
		],
		"next_id": 88,
		"achv_type": 10,
		"id": 87
	},
	"88": {
		"type_child": 5,
		"achv_parm": 30,
		"name": "小妖总等级",
		"disc": "小妖总等级达到 30级",
		"reward_1": [
			"3",
			"0",
			"50"
		],
		"next_id": 89,
		"achv_type": 10,
		"id": 88
	},
	"89": {
		"type_child": 6,
		"achv_parm": 50,
		"name": "小妖总等级",
		"disc": "小妖总等级达到 50级",
		"reward_1": [
			"3",
			"0",
			"50"
		],
		"next_id": 90,
		"achv_type": 10,
		"id": 89
	},
	"90": {
		"type_child": 7,
		"achv_parm": 100,
		"name": "小妖总等级",
		"disc": "小妖总等级达到 100级",
		"reward_1": [
			"3",
			"0",
			"50"
		],
		"next_id": 91,
		"achv_type": 10,
		"id": 90
	},
	"91": {
		"type_child": 8,
		"achv_parm": 200,
		"name": "小妖总等级",
		"disc": "小妖总等级达到 200级",
		"reward_1": [
			"3",
			"0",
			"50"
		],
		"next_id": 92,
		"achv_type": 10,
		"id": 91
	},
	"92": {
		"type_child": 9,
		"achv_parm": 500,
		"name": "小妖总等级",
		"disc": "小妖总等级达到 500级",
		"reward_1": [
			"3",
			"0",
			"50"
		],
		"next_id": 0,
		"achv_type": 10,
		"id": 92
	},
	"93": {
		"type_child": 1,
		"achv_parm": 1,
		"name": "拥有装备品质",
		"disc": "拥有 5 品质装备",
		"reward_1": [
			"3",
			"0",
			"50"
		],
		"next_id": 94,
		"achv_type": 11,
		"id": 93
	},
	"94": {
		"type_child": 2,
		"achv_parm": 2,
		"name": "拥有装备品质",
		"disc": "拥有 10 品质装备",
		"reward_1": [
			"3",
			"0",
			"50"
		],
		"next_id": 95,
		"achv_type": 11,
		"id": 94
	},
	"95": {
		"type_child": 3,
		"achv_parm": 3,
		"name": "拥有装备品质",
		"disc": "拥有 20 品质装备",
		"reward_1": [
			"3",
			"0",
			"50"
		],
		"next_id": 96,
		"achv_type": 11,
		"id": 95
	},
	"96": {
		"type_child": 4,
		"achv_parm": 4,
		"name": "拥有装备品质",
		"disc": "拥有 40 品质装备",
		"reward_1": [
			"3",
			"0",
			"50"
		],
		"next_id": 97,
		"achv_type": 11,
		"id": 96
	},
	"97": {
		"type_child": 5,
		"achv_parm": 5,
		"name": "拥有装备品质",
		"disc": "拥有 80 品质装备",
		"reward_1": [
			"3",
			"0",
			"50"
		],
		"next_id": 98,
		"achv_type": 11,
		"id": 97
	},
	"98": {
		"type_child": 6,
		"achv_parm": 6,
		"name": "拥有装备品质",
		"disc": "拥有 160 品质装备",
		"reward_1": [
			"3",
			"0",
			"50"
		],
		"next_id": 0,
		"achv_type": 11,
		"id": 98
	},
	"99": {
		"type_child": 1,
		"achv_parm": 1,
		"name": "拥有装备数量",
		"disc": "拥有 1 件装备",
		"reward_1": [
			"3",
			"0",
			"50"
		],
		"next_id": 100,
		"achv_type": 12,
		"id": 99
	},
	"100": {
		"type_child": 2,
		"achv_parm": 3,
		"name": "拥有装备数量",
		"disc": "拥有 3 件装备",
		"reward_1": [
			"3",
			"0",
			"50"
		],
		"next_id": 101,
		"achv_type": 12,
		"id": 100
	},
	"101": {
		"type_child": 3,
		"achv_parm": 5,
		"name": "拥有装备数量",
		"disc": "拥有 5 件装备",
		"reward_1": [
			"3",
			"0",
			"50"
		],
		"next_id": 102,
		"achv_type": 12,
		"id": 101
	},
	"102": {
		"type_child": 4,
		"achv_parm": 7,
		"name": "拥有装备数量",
		"disc": "拥有 7 件装备",
		"reward_1": [
			"3",
			"0",
			"50"
		],
		"next_id": 103,
		"achv_type": 12,
		"id": 102
	},
	"103": {
		"type_child": 5,
		"achv_parm": 9,
		"name": "拥有装备数量",
		"disc": "拥有 9 件装备",
		"reward_1": [
			"3",
			"0",
			"50"
		],
		"next_id": 104,
		"achv_type": 12,
		"id": 103
	},
	"104": {
		"type_child": 6,
		"achv_parm": 11,
		"name": "拥有装备数量",
		"disc": "拥有 11 件装备",
		"reward_1": [
			"3",
			"0",
			"50"
		],
		"next_id": 105,
		"achv_type": 12,
		"id": 104
	},
	"105": {
		"type_child": 7,
		"achv_parm": 13,
		"name": "拥有装备数量",
		"disc": "拥有 13 件装备",
		"reward_1": [
			"3",
			"0",
			"50"
		],
		"next_id": 106,
		"achv_type": 12,
		"id": 105
	},
	"106": {
		"type_child": 8,
		"achv_parm": 15,
		"name": "拥有装备数量",
		"disc": "拥有 15 件装备",
		"reward_1": [
			"3",
			"0",
			"50"
		],
		"next_id": 0,
		"achv_type": 12,
		"id": 106
	},
	"107": {
		"type_child": 1,
		"achv_parm": 3,
		"name": "开启巡山",
		"disc": "开启第 3个巡山",
		"reward_1": [
			"3",
			"0",
			"50"
		],
		"next_id": 108,
		"achv_type": 13,
		"id": 107
	},
	"108": {
		"type_child": 2,
		"achv_parm": 5,
		"name": "开启巡山",
		"disc": "开启第 5个巡山",
		"reward_1": [
			"3",
			"0",
			"50"
		],
		"next_id": 109,
		"achv_type": 13,
		"id": 108
	},
	"109": {
		"type_child": 3,
		"achv_parm": 7,
		"name": "开启巡山",
		"disc": "开启第 7个巡山",
		"reward_1": [
			"3",
			"0",
			"50"
		],
		"next_id": 110,
		"achv_type": 13,
		"id": 109
	},
	"110": {
		"type_child": 4,
		"achv_parm": 9,
		"name": "开启巡山",
		"disc": "开启第 9个巡山",
		"reward_1": [
			"3",
			"0",
			"50"
		],
		"next_id": 111,
		"achv_type": 13,
		"id": 110
	},
	"111": {
		"type_child": 5,
		"achv_parm": 12,
		"name": "开启巡山",
		"disc": "开启第 12个巡山",
		"reward_1": [
			"3",
			"0",
			"50"
		],
		"next_id": 112,
		"achv_type": 13,
		"id": 111
	},
	"112": {
		"type_child": 6,
		"achv_parm": 16,
		"name": "开启巡山",
		"disc": "开启第 16个巡山",
		"reward_1": [
			"3",
			"0",
			"50"
		],
		"next_id": 113,
		"achv_type": 13,
		"id": 112
	},
	"113": {
		"type_child": 7,
		"achv_parm": 20,
		"name": "开启巡山",
		"disc": "开启第 20个巡山",
		"reward_1": [
			"3",
			"0",
			"50"
		],
		"next_id": 114,
		"achv_type": 13,
		"id": 113
	},
	"114": {
		"type_child": 8,
		"achv_parm": 25,
		"name": "开启巡山",
		"disc": "开启第 25个巡山",
		"reward_1": [
			"3",
			"0",
			"50"
		],
		"next_id": 115,
		"achv_type": 13,
		"id": 114
	},
	"115": {
		"type_child": 9,
		"achv_parm": 30,
		"name": "开启巡山",
		"disc": "开启第 30个巡山",
		"reward_1": [
			"3",
			"0",
			"50"
		],
		"next_id": 0,
		"achv_type": 13,
		"id": 115
	},
	"116": {
		"type_child": 1,
		"achv_parm": 5,
		"name": "斗法获胜场次",
		"disc": "在斗法中取得 5 场胜利",
		"reward_1": [
			"3",
			"0",
			"50"
		],
		"next_id": 117,
		"achv_type": 14,
		"id": 116
	},
	"117": {
		"type_child": 2,
		"achv_parm": 10,
		"name": "斗法获胜场次",
		"disc": "在斗法中取得 10 场胜利",
		"reward_1": [
			"3",
			"0",
			"50"
		],
		"next_id": 118,
		"achv_type": 14,
		"id": 117
	},
	"118": {
		"type_child": 3,
		"achv_parm": 15,
		"name": "斗法获胜场次",
		"disc": "在斗法中取得 15 场胜利",
		"reward_1": [
			"3",
			"0",
			"50"
		],
		"next_id": 119,
		"achv_type": 14,
		"id": 118
	},
	"119": {
		"type_child": 4,
		"achv_parm": 20,
		"name": "斗法获胜场次",
		"disc": "在斗法中取得 20 场胜利",
		"reward_1": [
			"3",
			"0",
			"50"
		],
		"next_id": 120,
		"achv_type": 14,
		"id": 119
	},
	"120": {
		"type_child": 5,
		"achv_parm": 30,
		"name": "斗法获胜场次",
		"disc": "在斗法中取得 30 场胜利",
		"reward_1": [
			"3",
			"0",
			"50"
		],
		"next_id": 121,
		"achv_type": 14,
		"id": 120
	},
	"121": {
		"type_child": 6,
		"achv_parm": 50,
		"name": "斗法获胜场次",
		"disc": "在斗法中取得 50 场胜利",
		"reward_1": [
			"3",
			"0",
			"50"
		],
		"next_id": 122,
		"achv_type": 14,
		"id": 121
	},
	"122": {
		"type_child": 7,
		"achv_parm": 100,
		"name": "斗法获胜场次",
		"disc": "在斗法中取得 100 场胜利",
		"reward_1": [
			"3",
			"0",
			"50"
		],
		"next_id": 123,
		"achv_type": 14,
		"id": 122
	},
	"123": {
		"type_child": 8,
		"achv_parm": 200,
		"name": "斗法获胜场次",
		"disc": "在斗法中取得 200 场胜利",
		"reward_1": [
			"3",
			"0",
			"50"
		],
		"next_id": 124,
		"achv_type": 14,
		"id": 123
	},
	"124": {
		"type_child": 9,
		"achv_parm": 500,
		"name": "斗法获胜场次",
		"disc": "在斗法中取得 500 场胜利",
		"reward_1": [
			"3",
			"0",
			"50"
		],
		"next_id": 0,
		"achv_type": 14,
		"id": 124
	},
	"125": {
		"type_child": 1,
		"achv_parm": 5,
		"name": "斗法连胜场次",
		"disc": "在斗法中取得 5 场连胜",
		"reward_1": [
			"3",
			"0",
			"50"
		],
		"next_id": 126,
		"achv_type": 15,
		"id": 125
	},
	"126": {
		"type_child": 2,
		"achv_parm": 10,
		"name": "斗法连胜场次",
		"disc": "在斗法中取得 10 场连胜",
		"reward_1": [
			"3",
			"0",
			"50"
		],
		"next_id": 127,
		"achv_type": 15,
		"id": 126
	},
	"127": {
		"type_child": 3,
		"achv_parm": 15,
		"name": "斗法连胜场次",
		"disc": "在斗法中取得 15 场连胜",
		"reward_1": [
			"3",
			"0",
			"50"
		],
		"next_id": 128,
		"achv_type": 15,
		"id": 127
	},
	"128": {
		"type_child": 4,
		"achv_parm": 20,
		"name": "斗法连胜场次",
		"disc": "在斗法中取得 20 场连胜",
		"reward_1": [
			"3",
			"0",
			"50"
		],
		"next_id": 129,
		"achv_type": 15,
		"id": 128
	},
	"129": {
		"type_child": 5,
		"achv_parm": 30,
		"name": "斗法连胜场次",
		"disc": "在斗法中取得 30 场连胜",
		"reward_1": [
			"3",
			"0",
			"50"
		],
		"next_id": 130,
		"achv_type": 15,
		"id": 129
	},
	"130": {
		"type_child": 6,
		"achv_parm": 50,
		"name": "斗法连胜场次",
		"disc": "在斗法中取得 50 场连胜",
		"reward_1": [
			"3",
			"0",
			"50"
		],
		"next_id": 0,
		"achv_type": 15,
		"id": 130
	}
}