{
	"1": {
		"chance": 0.1,
		"resource": "item_kill_effect",
		"tip": "召唤如来神掌秒杀所有小怪（ID小于300），对非小怪造成其生命上限20%的伤害",
		"cd": 5,
		"id": 1,
		"name": "五指山"
	},
	"3": {
		"chance": 0.1,
		"resource": "item_hp_effect",
		"tip": "回复全体友军50%生命",
		"cd": 5,
		"id": 3,
		"name": "蟠桃"
	},
	"4": {
		"chance": 0.005,
		"resource": "item_reborn_effect",
		"tip": "获得1次转生次数",
		"cd": 4320,
		"id": 4,
		"name": "月光宝盒"
	},
	"5": {
		"chance": 0.1,
		"resource": "item_gold_effect",
		"tip": "获得半小时的铜钱产出",
		"cd": 2,
		"id": 5,
		"name": "小财神"
	},
	"6": {
		"chance": 0.05,
		"resource": "item_diamond_effect",
		"tip": "随机获得5-10获得元宝",
		"cd": 5,
		"id": 6,
		"name": "大财神"
	}
}